{
  "data": [
    {
      "REPORT_DATE": "2026-05-01 00:00:00",
      "TIME": "2026年05月份",
      "RMB_LOAN": 4965,
      "RMB_LOAN_SAME": -16.17423603,
      "RMB_LOAN_SEQUENTIAL": 223.93909136,
      "RMB_LOAN_ACCUMULATE": 89955,
      "LOAN_ACCUMULATE_SAME": -13.30724825
    },
    {
      "REPORT_DATE": "2026-04-01 00:00:00",
      "TIME": "2026年04月份",
      "RMB_LOAN": -4006,
      "RMB_LOAN_SAME": -553.16742081,
      "RMB_LOAN_SEQUENTIAL": -112.70858448,
      "RMB_LOAN_ACCUMULATE": 84990,
      "LOAN_ACCUMULATE_SAME": -13.13368765
    },
    {
      "REPORT_DATE": "2026-03-01 00:00:00",
      "TIME": "2026年03月份",
      "RMB_LOAN": 31522,
      "RMB_LOAN_SAME": -17.55505571,
      "RMB_LOAN_SEQUENTIAL": 272.68857886,
      "RMB_LOAN_ACCUMULATE": 88996,
      "LOAN_ACCUMULATE_SAME": -8.20990965
    },
    {
      "REPORT_DATE": "2026-02-01 00:00:00",
      "TIME": "2026年02月份",
      "RMB_LOAN": 8458,
      "RMB_LOAN_SAME": 29.56495098,
      "RMB_LOAN_SEQUENTIAL": -82.74440999,
      "RMB_LOAN_ACCUMULATE": 57474,
      "LOAN_ACCUMULATE_SAME": -2.12526821
    },
    {
      "REPORT_DATE": "2026-01-01 00:00:00",
      "TIME": "2026年01月份",
      "RMB_LOAN": 49016,
      "RMB_LOAN_SAME": -6.08882247,
      "RMB_LOAN_SEQUENTIAL": 399.95920033,
      "RMB_LOAN_ACCUMULATE": 49016,
      "LOAN_ACCUMULATE_SAME": -6.08882247
    },
    {
      "REPORT_DATE": "2025-12-01 00:00:00",
      "TIME": "2025年12月份",
      "RMB_LOAN": 9804,
      "RMB_LOAN_SAME": 16.68650321,
      "RMB_LOAN_SEQUENTIAL": 139.35546875,
      "RMB_LOAN_ACCUMULATE": 159147,
      "LOAN_ACCUMULATE_SAME": -6.65591366
    },
    {
      "REPORT_DATE": "2025-11-01 00:00:00",
      "TIME": "2025年11月份",
      "RMB_LOAN": 4096,
      "RMB_LOAN_SAME": -21.47239264,
      "RMB_LOAN_SEQUENTIAL": 2759.74025974,
      "RMB_LOAN_ACCUMULATE": 149343,
      "LOAN_ACCUMULATE_SAME": -7.86585479
    },
    {
      "REPORT_DATE": "2025-10-01 00:00:00",
      "TIME": "2025年10月份",
      "RMB_LOAN": -154,
      "RMB_LOAN_SAME": -105.19392917,
      "RMB_LOAN_SEQUENTIAL": -100.95765189,
      "RMB_LOAN_ACCUMULATE": 145247,
      "LOAN_ACCUMULATE_SAME": -7.4134513
    },
    {
      "REPORT_DATE": "2025-09-01 00:00:00",
      "TIME": "2025年09月份",
      "RMB_LOAN": 16081,
      "RMB_LOAN_SAME": -18.54422044,
      "RMB_LOAN_SEQUENTIAL": 157.17255717,
      "RMB_LOAN_ACCUMULATE": 145401,
      "LOAN_ACCUMULATE_SAME": -5.52978325
    },
    {
      "REPORT_DATE": "2025-08-01 00:00:00",
      "TIME": "2025年08月份",
      "RMB_LOAN": 6253,
      "RMB_LOAN_SAME": -39.93852656,
      "RMB_LOAN_SEQUENTIAL": 245.55400372,
      "RMB_LOAN_ACCUMULATE": 129320,
      "LOAN_ACCUMULATE_SAME": -3.61481702
    },
    {
      "REPORT_DATE": "2025-07-01 00:00:00",
      "TIME": "2025年07月份",
      "RMB_LOAN": -4296,
      "RMB_LOAN_SAME": -431.68316832,
      "RMB_LOAN_SEQUENTIAL": -118.20338983,
      "RMB_LOAN_ACCUMULATE": 123067,
      "LOAN_ACCUMULATE_SAME": -0.55915125
    },
    {
      "REPORT_DATE": "2025-06-01 00:00:00",
      "TIME": "2025年06月份",
      "RMB_LOAN": 23600,
      "RMB_LOAN_SAME": 7.62986273,
      "RMB_LOAN_SEQUENTIAL": 298.44673307,
      "RMB_LOAN_ACCUMULATE": 127363,
      "LOAN_ACCUMULATE_SAME": 2.24457521
    },
    {
      "REPORT_DATE": "2025-05-01 00:00:00",
      "TIME": "2025年05月份",
      "RMB_LOAN": 5923,
      "RMB_LOAN_SAME": -27.74185678,
      "RMB_LOAN_SEQUENTIAL": 570.02262443,
      "RMB_LOAN_ACCUMULATE": 103763,
      "LOAN_ACCUMULATE_SAME": 1.09411535
    },
    {
      "REPORT_DATE": "2025-04-01 00:00:00",
      "TIME": "2025年04月份",
      "RMB_LOAN": 884,
      "RMB_LOAN_SAME": -73.60406091,
      "RMB_LOAN_SEQUENTIAL": -97.68792175,
      "RMB_LOAN_ACCUMULATE": 97840,
      "LOAN_ACCUMULATE_SAME": 3.59687854
    },
    {
      "REPORT_DATE": "2025-03-01 00:00:00",
      "TIME": "2025年03月份",
      "RMB_LOAN": 38234,
      "RMB_LOAN_SAME": 16.14216282,
      "RMB_LOAN_SEQUENTIAL": 485.69240196,
      "RMB_LOAN_ACCUMULATE": 96956,
      "LOAN_ACCUMULATE_SAME": 6.43511098
    },
    {
      "REPORT_DATE": "2025-02-01 00:00:00",
      "TIME": "2025年02月份",
      "RMB_LOAN": 6528,
      "RMB_LOAN_SAME": -33.20372455,
      "RMB_LOAN_SEQUENTIAL": -87.49281527,
      "RMB_LOAN_ACCUMULATE": 58722,
      "LOAN_ACCUMULATE_SAME": 0.94200158
    },
    {
      "REPORT_DATE": "2025-01-01 00:00:00",
      "TIME": "2025年01月份",
      "RMB_LOAN": 52194,
      "RMB_LOAN_SAME": 7.83661495,
      "RMB_LOAN_SEQUENTIAL": 521.2092359,
      "RMB_LOAN_ACCUMULATE": 52194,
      "LOAN_ACCUMULATE_SAME": 7.83661495
    },
    {
      "REPORT_DATE": "2024-12-01 00:00:00",
      "TIME": "2024年12月份",
      "RMB_LOAN": 8402,
      "RMB_LOAN_SAME": -24.25171295,
      "RMB_LOAN_SEQUENTIAL": 61.08128834,
      "RMB_LOAN_ACCUMULATE": 170495,
      "LOAN_ACCUMULATE_SAME": -23.28407772
    },
    {
      "REPORT_DATE": "2024-11-01 00:00:00",
      "TIME": "2024年11月份",
      "RMB_LOAN": 5216,
      "RMB_LOAN_SAME": -53.09352518,
      "RMB_LOAN_SEQUENTIAL": 75.91905565,
      "RMB_LOAN_ACCUMULATE": 162093,
      "LOAN_ACCUMULATE_SAME": -23.23324651
    },
    {
      "REPORT_DATE": "2024-10-01 00:00:00",
      "TIME": "2024年10月份",
      "RMB_LOAN": 2965,
      "RMB_LOAN_SAME": -38.70167459,
      "RMB_LOAN_SEQUENTIAL": -84.98125823,
      "RMB_LOAN_ACCUMULATE": 156877,
      "LOAN_ACCUMULATE_SAME": -21.57326401
    },
    {
      "REPORT_DATE": "2024-09-01 00:00:00",
      "TIME": "2024年09月份",
      "RMB_LOAN": 19742,
      "RMB_LOAN_SAME": -22.18061414,
      "RMB_LOAN_SEQUENTIAL": 89.62635674,
      "RMB_LOAN_ACCUMULATE": 153912,
      "LOAN_ACCUMULATE_SAME": -21.14881169
    },
    {
      "REPORT_DATE": "2024-08-01 00:00:00",
      "TIME": "2024年08月份",
      "RMB_LOAN": 10411,
      "RMB_LOAN_SAME": -22.37548464,
      "RMB_LOAN_SEQUENTIAL": 1388.49009901,
      "RMB_LOAN_ACCUMULATE": 134170,
      "LOAN_ACCUMULATE_SAME": -20.99467684
    },
    {
      "REPORT_DATE": "2024-07-01 00:00:00",
      "TIME": "2024年07月份",
      "RMB_LOAN": -808,
      "RMB_LOAN_SAME": -321.97802198,
      "RMB_LOAN_SEQUENTIAL": -103.68495462,
      "RMB_LOAN_ACCUMULATE": 123759,
      "LOAN_ACCUMULATE_SAME": -20.87627548
    },
    {
      "REPORT_DATE": "2024-06-01 00:00:00",
      "TIME": "2024年06月份",
      "RMB_LOAN": 21927,
      "RMB_LOAN_SAME": -32.3512171,
      "RMB_LOAN_SEQUENTIAL": 167.50030499,
      "RMB_LOAN_ACCUMULATE": 124567,
      "LOAN_ACCUMULATE_SAME": -20.17392084
    },
    {
      "REPORT_DATE": "2024-05-01 00:00:00",
      "TIME": "2024年05月份",
      "RMB_LOAN": 8197,
      "RMB_LOAN_SAME": -32.91595057,
      "RMB_LOAN_SEQUENTIAL": 144.75962974,
      "RMB_LOAN_ACCUMULATE": 102640,
      "LOAN_ACCUMULATE_SAME": -16.9814373
    },
    {
      "REPORT_DATE": "2024-04-01 00:00:00",
      "TIME": "2024年04月份",
      "RMB_LOAN": 3349,
      "RMB_LOAN_SAME": -24.41886707,
      "RMB_LOAN_SEQUENTIAL": -89.82685298,
      "RMB_LOAN_ACCUMULATE": 94443,
      "LOAN_ACCUMULATE_SAME": -15.23389818
    },
    {
      "REPORT_DATE": "2024-03-01 00:00:00",
      "TIME": "2024年03月份",
      "RMB_LOAN": 32920,
      "RMB_LOAN_SAME": -16.63078988,
      "RMB_LOAN_SEQUENTIAL": 236.84641359,
      "RMB_LOAN_ACCUMULATE": 91094,
      "LOAN_ACCUMULATE_SAME": -14.85348413
    },
    {
      "REPORT_DATE": "2024-02-01 00:00:00",
      "TIME": "2024年02月份",
      "RMB_LOAN": 9773,
      "RMB_LOAN_SAME": -46.25494941,
      "RMB_LOAN_SEQUENTIAL": -79.80826842,
      "RMB_LOAN_ACCUMULATE": 58174,
      "LOAN_ACCUMULATE_SAME": -13.81374263
    },
    {
      "REPORT_DATE": "2024-01-01 00:00:00",
      "TIME": "2024年01月份",
      "RMB_LOAN": 48401,
      "RMB_LOAN_SAME": -1.85140122,
      "RMB_LOAN_SEQUENTIAL": 336.35953841,
      "RMB_LOAN_ACCUMULATE": 48401,
      "LOAN_ACCUMULATE_SAME": -1.85140122
    },
    {
      "REPORT_DATE": "2023-12-01 00:00:00",
      "TIME": "2023年12月份",
      "RMB_LOAN": 11092,
      "RMB_LOAN_SAME": -22.977571,
      "RMB_LOAN_SEQUENTIAL": -0.25179856,
      "RMB_LOAN_ACCUMULATE": 222242,
      "LOAN_ACCUMULATE_SAME": 6.26114647
    },
    {
      "REPORT_DATE": "2023-11-01 00:00:00",
      "TIME": "2023年11月份",
      "RMB_LOAN": 11120,
      "RMB_LOAN_SAME": -2.86512928,
      "RMB_LOAN_SEQUENTIAL": 129.89456275,
      "RMB_LOAN_ACCUMULATE": 211150,
      "LOAN_ACCUMULATE_SAME": 8.42327955
    },
    {
      "REPORT_DATE": "2023-10-01 00:00:00",
      "TIME": "2023年10月份",
      "RMB_LOAN": 4837,
      "RMB_LOAN_SAME": 9.16271722,
      "RMB_LOAN_SEQUENTIAL": -80.93342268,
      "RMB_LOAN_ACCUMULATE": 200030,
      "LOAN_ACCUMULATE_SAME": 9.12830473
    },
    {
      "REPORT_DATE": "2023-09-01 00:00:00",
      "TIME": "2023年09月份",
      "RMB_LOAN": 25369,
      "RMB_LOAN_SAME": -1.23413533,
      "RMB_LOAN_SEQUENTIAL": 89.15150611,
      "RMB_LOAN_ACCUMULATE": 195193,
      "LOAN_ACCUMULATE_SAME": 9.12745224
    },
    {
      "REPORT_DATE": "2023-08-01 00:00:00",
      "TIME": "2023年08月份",
      "RMB_LOAN": 13412,
      "RMB_LOAN_SAME": 0.50959233,
      "RMB_LOAN_SEQUENTIAL": 3584.61538462,
      "RMB_LOAN_ACCUMULATE": 169824,
      "LOAN_ACCUMULATE_SAME": 10.8649245
    },
    {
      "REPORT_DATE": "2023-07-01 00:00:00",
      "TIME": "2023年07月份",
      "RMB_LOAN": 364,
      "RMB_LOAN_SAME": -91.09589041,
      "RMB_LOAN_SEQUENTIAL": -98.8769938,
      "RMB_LOAN_ACCUMULATE": 156412,
      "LOAN_ACCUMULATE_SAME": 11.85308609
    },
    {
      "REPORT_DATE": "2023-06-01 00:00:00",
      "TIME": "2023年06月份",
      "RMB_LOAN": 32413,
      "RMB_LOAN_SAME": 6.13294041,
      "RMB_LOAN_SEQUENTIAL": 165.26720681,
      "RMB_LOAN_ACCUMULATE": 156048,
      "LOAN_ACCUMULATE_SAME": 14.95333299
    },
    {
      "REPORT_DATE": "2023-05-01 00:00:00",
      "TIME": "2023年05月份",
      "RMB_LOAN": 12219,
      "RMB_LOAN_SAME": -32.97312123,
      "RMB_LOAN_SEQUENTIAL": 175.76167908,
      "RMB_LOAN_ACCUMULATE": 123635,
      "LOAN_ACCUMULATE_SAME": 17.5137108
    },
    {
      "REPORT_DATE": "2023-04-01 00:00:00",
      "TIME": "2023年04月份",
      "RMB_LOAN": 4431,
      "RMB_LOAN_SAME": 22.53871681,
      "RMB_LOAN_SEQUENTIAL": -88.77858536,
      "RMB_LOAN_ACCUMULATE": 111416,
      "LOAN_ACCUMULATE_SAME": 28.09528737
    },
    {
      "REPORT_DATE": "2023-03-01 00:00:00",
      "TIME": "2023年03月份",
      "RMB_LOAN": 39487,
      "RMB_LOAN_SAME": 22.28484717,
      "RMB_LOAN_SEQUENTIAL": 117.15244171,
      "RMB_LOAN_ACCUMULATE": 106985,
      "LOAN_ACCUMULATE_SAME": 28.33631227
    },
    {
      "REPORT_DATE": "2023-02-01 00:00:00",
      "TIME": "2023年02月份",
      "RMB_LOAN": 18184,
      "RMB_LOAN_SAME": 100.17613386,
      "RMB_LOAN_SEQUENTIAL": -63.12608995,
      "RMB_LOAN_ACCUMULATE": 67498,
      "LOAN_ACCUMULATE_SAME": 32.16243734
    },
    {
      "REPORT_DATE": "2023-01-01 00:00:00",
      "TIME": "2023年01月份",
      "RMB_LOAN": 49314,
      "RMB_LOAN_SAME": 17.44784224,
      "RMB_LOAN_SEQUENTIAL": 242.43455316,
      "RMB_LOAN_ACCUMULATE": 49314,
      "LOAN_ACCUMULATE_SAME": 17.44784224
    },
    {
      "REPORT_DATE": "2022-12-01 00:00:00",
      "TIME": "2022年12月份",
      "RMB_LOAN": 14401,
      "RMB_LOAN_SAME": 39.14009662,
      "RMB_LOAN_SEQUENTIAL": 25.79489867,
      "RMB_LOAN_ACCUMULATE": 209147,
      "LOAN_ACCUMULATE_SAME": 4.88606046
    },
    {
      "REPORT_DATE": "2022-11-01 00:00:00",
      "TIME": "2022年11月份",
      "RMB_LOAN": 11448,
      "RMB_LOAN_SAME": -12.08048537,
      "RMB_LOAN_SEQUENTIAL": 158.36154367,
      "RMB_LOAN_ACCUMULATE": 194746,
      "LOAN_ACCUMULATE_SAME": 3.01077999
    },
    {
      "REPORT_DATE": "2022-10-01 00:00:00",
      "TIME": "2022年10月份",
      "RMB_LOAN": 4431,
      "RMB_LOAN_SAME": -42.84055728,
      "RMB_LOAN_SEQUENTIAL": -82.74935763,
      "RMB_LOAN_ACCUMULATE": 183298,
      "LOAN_ACCUMULATE_SAME": 4.12706708
    },
    {
      "REPORT_DATE": "2022-09-01 00:00:00",
      "TIME": "2022年09月份",
      "RMB_LOAN": 25686,
      "RMB_LOAN_SAME": 44.66910729,
      "RMB_LOAN_SEQUENTIAL": 92.49100719,
      "RMB_LOAN_ACCUMULATE": 178867,
      "LOAN_ACCUMULATE_SAME": 6.29066858
    },
    {
      "REPORT_DATE": "2022-08-01 00:00:00",
      "TIME": "2022年08月份",
      "RMB_LOAN": 13344,
      "RMB_LOAN_SAME": 4.96342327,
      "RMB_LOAN_SEQUENTIAL": 226.41878669,
      "RMB_LOAN_ACCUMULATE": 153181,
      "LOAN_ACCUMULATE_SAME": 1.76381489
    },
    {
      "REPORT_DATE": "2022-07-01 00:00:00",
      "TIME": "2022年07月份",
      "RMB_LOAN": 4088,
      "RMB_LOAN_SAME": -51.28113455,
      "RMB_LOAN_SEQUENTIAL": -86.61427636,
      "RMB_LOAN_ACCUMULATE": 139837,
      "LOAN_ACCUMULATE_SAME": 1.4686568
    },
    {
      "REPORT_DATE": "2022-06-01 00:00:00",
      "TIME": "2022年06月份",
      "RMB_LOAN": 30540,
      "RMB_LOAN_SAME": 31.74014321,
      "RMB_LOAN_SEQUENTIAL": 67.52605595,
      "RMB_LOAN_ACCUMULATE": 135749,
      "LOAN_ACCUMULATE_SAME": 4.88865881
    },
    {
      "REPORT_DATE": "2022-05-01 00:00:00",
      "TIME": "2022年05月份",
      "RMB_LOAN": 18230,
      "RMB_LOAN_SAME": 27.5360291,
      "RMB_LOAN_SEQUENTIAL": 404.14823009,
      "RMB_LOAN_ACCUMULATE": 105209,
      "LOAN_ACCUMULATE_SAME": -0.97044428
    },
    {
      "REPORT_DATE": "2022-04-01 00:00:00",
      "TIME": "2022年04月份",
      "RMB_LOAN": 3616,
      "RMB_LOAN_SAME": -71.83800623,
      "RMB_LOAN_SEQUENTIAL": -88.80183333,
      "RMB_LOAN_ACCUMULATE": 86979,
      "LOAN_ACCUMULATE_SAME": -5.40208383
    },
    {
      "REPORT_DATE": "2022-03-01 00:00:00",
      "TIME": "2022年03月份",
      "RMB_LOAN": 32291,
      "RMB_LOAN_SAME": 17.37486823,
      "RMB_LOAN_SEQUENTIAL": 255.47115808,
      "RMB_LOAN_ACCUMULATE": 83363,
      "LOAN_ACCUMULATE_SAME": 5.381387
    },
    {
      "REPORT_DATE": "2022-02-01 00:00:00",
      "TIME": "2022年02月份",
      "RMB_LOAN": 9084,
      "RMB_LOAN_SAME": -32.27465891,
      "RMB_LOAN_SEQUENTIAL": -78.36524721,
      "RMB_LOAN_ACCUMULATE": 51072,
      "LOAN_ACCUMULATE_SAME": -1.01366411
    },
    {
      "REPORT_DATE": "2022-01-01 00:00:00",
      "TIME": "2022年01月份",
      "RMB_LOAN": 41988,
      "RMB_LOAN_SAME": 9.96804777,
      "RMB_LOAN_SEQUENTIAL": 305.68115942,
      "RMB_LOAN_ACCUMULATE": 41988,
      "LOAN_ACCUMULATE_SAME": 9.96804777
    },
    {
      "REPORT_DATE": "2021-12-01 00:00:00",
      "TIME": "2021年12月份",
      "RMB_LOAN": 10350,
      "RMB_LOAN_SAME": -9.67009949,
      "RMB_LOAN_SEQUENTIAL": -20.51301743,
      "RMB_LOAN_ACCUMULATE": 199404,
      "LOAN_ACCUMULATE_SAME": -0.45180197
    },
    {
      "REPORT_DATE": "2021-11-01 00:00:00",
      "TIME": "2021年11月份",
      "RMB_LOAN": 13021,
      "RMB_LOAN_SAME": -14.94545692,
      "RMB_LOAN_SEQUENTIAL": 67.96955624,
      "RMB_LOAN_ACCUMULATE": 189054,
      "LOAN_ACCUMULATE_SAME": 0.10749215
    },
    {
      "REPORT_DATE": "2021-10-01 00:00:00",
      "TIME": "2021年10月份",
      "RMB_LOAN": 7752,
      "RMB_LOAN_SAME": 16.34398919,
      "RMB_LOAN_SEQUENTIAL": -56.33905942,
      "RMB_LOAN_ACCUMULATE": 176033,
      "LOAN_ACCUMULATE_SAME": 1.4353874
    },
    {
      "REPORT_DATE": "2021-09-01 00:00:00",
      "TIME": "2021年09月份",
      "RMB_LOAN": 17755,
      "RMB_LOAN_SAME": -7.38615617,
      "RMB_LOAN_SEQUENTIAL": 39.66019036,
      "RMB_LOAN_ACCUMULATE": 168281,
      "LOAN_ACCUMULATE_SAME": 0.84012967
    },
    {
      "REPORT_DATE": "2021-08-01 00:00:00",
      "TIME": "2021年08月份",
      "RMB_LOAN": 12713,
      "RMB_LOAN_SAME": -10.47813534,
      "RMB_LOAN_SEQUENTIAL": 51.50756763,
      "RMB_LOAN_ACCUMULATE": 150526,
      "LOAN_ACCUMULATE_SAME": 1.90781813
    },
    {
      "REPORT_DATE": "2021-07-01 00:00:00",
      "TIME": "2021年07月份",
      "RMB_LOAN": 8391,
      "RMB_LOAN_SAME": -17.90431465,
      "RMB_LOAN_SEQUENTIAL": -63.8038133,
      "RMB_LOAN_ACCUMULATE": 137813,
      "LOAN_ACCUMULATE_SAME": 3.22529905
    },
    {
      "REPORT_DATE": "2021-06-01 00:00:00",
      "TIME": "2021年06月份",
      "RMB_LOAN": 23182,
      "RMB_LOAN_SAME": 21.82458353,
      "RMB_LOAN_SEQUENTIAL": 62.17993564,
      "RMB_LOAN_ACCUMULATE": 129422,
      "LOAN_ACCUMULATE_SAME": 4.97704524
    },
    {
      "REPORT_DATE": "2021-05-01 00:00:00",
      "TIME": "2021年05月份",
      "RMB_LOAN": 14294,
      "RMB_LOAN_SAME": -7.7925429,
      "RMB_LOAN_SEQUENTIAL": 11.32398754,
      "RMB_LOAN_ACCUMULATE": 106240,
      "LOAN_ACCUMULATE_SAME": 1.90203056
    },
    {
      "REPORT_DATE": "2021-04-01 00:00:00",
      "TIME": "2021年04月份",
      "RMB_LOAN": 12840,
      "RMB_LOAN_SAME": -20.93109182,
      "RMB_LOAN_SEQUENTIAL": -53.32775981,
      "RMB_LOAN_ACCUMULATE": 91946,
      "LOAN_ACCUMULATE_SAME": 3.59529041
    },
    {
      "REPORT_DATE": "2021-03-01 00:00:00",
      "TIME": "2021年03月份",
      "RMB_LOAN": 27511,
      "RMB_LOAN_SAME": -9.47351102,
      "RMB_LOAN_SEQUENTIAL": 105.10698576,
      "RMB_LOAN_ACCUMULATE": 79106,
      "LOAN_ACCUMULATE_SAME": 9.08764962
    },
    {
      "REPORT_DATE": "2021-02-01 00:00:00",
      "TIME": "2021年02月份",
      "RMB_LOAN": 13413,
      "RMB_LOAN_SAME": 86.23993335,
      "RMB_LOAN_SEQUENTIAL": -64.87088157,
      "RMB_LOAN_ACCUMULATE": 51595,
      "LOAN_ACCUMULATE_SAME": 22.47780468
    },
    {
      "REPORT_DATE": "2021-01-01 00:00:00",
      "TIME": "2021年01月份",
      "RMB_LOAN": 38182,
      "RMB_LOAN_SAME": 9.32882831,
      "RMB_LOAN_SEQUENTIAL": 233.23442136,
      "RMB_LOAN_ACCUMULATE": 38182,
      "LOAN_ACCUMULATE_SAME": 9.32882831
    },
    {
      "REPORT_DATE": "2020-12-01 00:00:00",
      "TIME": "2020年12月份",
      "RMB_LOAN": 11458,
      "RMB_LOAN_SAME": 6.38993502,
      "RMB_LOAN_SEQUENTIAL": -25.1551375,
      "RMB_LOAN_ACCUMULATE": 200309,
      "LOAN_ACCUMULATE_SAME": 18.64193523
    },
    {
      "REPORT_DATE": "2020-11-01 00:00:00",
      "TIME": "2020年11月份",
      "RMB_LOAN": 15309,
      "RMB_LOAN_SAME": 12.29227217,
      "RMB_LOAN_SEQUENTIAL": 129.76136875,
      "RMB_LOAN_ACCUMULATE": 188851,
      "LOAN_ACCUMULATE_SAME": 19.4767292
    },
    {
      "REPORT_DATE": "2020-10-01 00:00:00",
      "TIME": "2020年10月份",
      "RMB_LOAN": 6663,
      "RMB_LOAN_SAME": 21.81792194,
      "RMB_LOAN_SEQUENTIAL": -65.24437953,
      "RMB_LOAN_ACCUMULATE": 173542,
      "LOAN_ACCUMULATE_SAME": 20.15488227
    },
    {
      "REPORT_DATE": "2020-09-01 00:00:00",
      "TIME": "2020年09月份",
      "RMB_LOAN": 19171,
      "RMB_LOAN_SAME": 8.84919544,
      "RMB_LOAN_SEQUENTIAL": 34.99753538,
      "RMB_LOAN_ACCUMULATE": 166879,
      "LOAN_ACCUMULATE_SAME": 20.08942403
    },
    {
      "REPORT_DATE": "2020-08-01 00:00:00",
      "TIME": "2020年08月份",
      "RMB_LOAN": 14201,
      "RMB_LOAN_SAME": 8.86011411,
      "RMB_LOAN_SEQUENTIAL": 38.93943841,
      "RMB_LOAN_ACCUMULATE": 147708,
      "LOAN_ACCUMULATE_SAME": 21.72080536
    },
    {
      "REPORT_DATE": "2020-07-01 00:00:00",
      "TIME": "2020年07月份",
      "RMB_LOAN": 10221,
      "RMB_LOAN_SAME": 26.40252104,
      "RMB_LOAN_SEQUENTIAL": -46.28724578,
      "RMB_LOAN_ACCUMULATE": 133507,
      "LOAN_ACCUMULATE_SAME": 23.2698621
    },
    {
      "REPORT_DATE": "2020-06-01 00:00:00",
      "TIME": "2020年06月份",
      "RMB_LOAN": 19029,
      "RMB_LOAN_SAME": 13.69489089,
      "RMB_LOAN_SEQUENTIAL": 22.75190298,
      "RMB_LOAN_ACCUMULATE": 123286,
      "LOAN_ACCUMULATE_SAME": 23.0171055
    },
    {
      "REPORT_DATE": "2020-05-01 00:00:00",
      "TIME": "2020年05月份",
      "RMB_LOAN": 15502,
      "RMB_LOAN_SAME": 30.75833094,
      "RMB_LOAN_SEQUENTIAL": -4.5384568,
      "RMB_LOAN_ACCUMULATE": 104257,
      "LOAN_ACCUMULATE_SAME": 24.88607802
    },
    {
      "REPORT_DATE": "2020-04-01 00:00:00",
      "TIME": "2020年04月份",
      "RMB_LOAN": 16239,
      "RMB_LOAN_SAME": 85.95351841,
      "RMB_LOAN_SEQUENTIAL": -46.56465943,
      "RMB_LOAN_ACCUMULATE": 88755,
      "LOAN_ACCUMULATE_SAME": 23.91411206
    },
    {
      "REPORT_DATE": "2020-03-01 00:00:00",
      "TIME": "2020年03月份",
      "RMB_LOAN": 30390,
      "RMB_LOAN_SAME": 55.17456208,
      "RMB_LOAN_SEQUENTIAL": 321.96612052,
      "RMB_LOAN_ACCUMULATE": 72516,
      "LOAN_ACCUMULATE_SAME": 15.29986223
    },
    {
      "REPORT_DATE": "2020-02-01 00:00:00",
      "TIME": "2020年02月份",
      "RMB_LOAN": 7202,
      "RMB_LOAN_SAME": -5.74090332,
      "RMB_LOAN_SEQUENTIAL": -79.37807811,
      "RMB_LOAN_ACCUMULATE": 42126,
      "LOAN_ACCUMULATE_SAME": -2.73153699
    },
    {
      "REPORT_DATE": "2020-01-01 00:00:00",
      "TIME": "2020年01月份",
      "RMB_LOAN": 34924,
      "RMB_LOAN_SAME": -2.08689029,
      "RMB_LOAN_SEQUENTIAL": 224.27667052,
      "RMB_LOAN_ACCUMULATE": 34924,
      "LOAN_ACCUMULATE_SAME": -2.08689029
    },
    {
      "REPORT_DATE": "2019-12-01 00:00:00",
      "TIME": "2019年12月份",
      "RMB_LOAN": 10769.81577,
      "RMB_LOAN_SAME": 16.03573881,
      "RMB_LOAN_SEQUENTIAL": -21.00286866,
      "RMB_LOAN_ACCUMULATE": 168834.906151,
      "LOAN_ACCUMULATE_SAME": 7.73550439
    },
    {
      "REPORT_DATE": "2019-11-01 00:00:00",
      "TIME": "2019年11月份",
      "RMB_LOAN": 13633.17324,
      "RMB_LOAN_SAME": 10.81782406,
      "RMB_LOAN_SEQUENTIAL": 149.25181354,
      "RMB_LOAN_ACCUMULATE": 158065.090381,
      "LOAN_ACCUMULATE_SAME": 7.21296599
    },
    {
      "REPORT_DATE": "2019-10-01 00:00:00",
      "TIME": "2019年10月份",
      "RMB_LOAN": 5469.638534,
      "RMB_LOAN_SAME": -23.40817705,
      "RMB_LOAN_SEQUENTIAL": -68.94446018,
      "RMB_LOAN_ACCUMULATE": 144431.917141,
      "LOAN_ACCUMULATE_SAME": 6.88477385
    },
    {
      "REPORT_DATE": "2019-09-01 00:00:00",
      "TIME": "2019年09月份",
      "RMB_LOAN": 17612.4407,
      "RMB_LOAN_SAME": 22.81180973,
      "RMB_LOAN_SEQUENTIAL": 35.01107699,
      "RMB_LOAN_ACCUMULATE": 138962.278607,
      "LOAN_ACCUMULATE_SAME": 8.57502331
    },
    {
      "REPORT_DATE": "2019-08-01 00:00:00",
      "TIME": "2019年08月份",
      "RMB_LOAN": 13045.18199,
      "RMB_LOAN_SAME": -0.7215885,
      "RMB_LOAN_SEQUENTIAL": 61.3290178,
      "RMB_LOAN_ACCUMULATE": 121349.837907,
      "LOAN_ACCUMULATE_SAME": 6.77848722
    },
    {
      "REPORT_DATE": "2019-07-01 00:00:00",
      "TIME": "2019年07月份",
      "RMB_LOAN": 8086.072901,
      "RMB_LOAN_SAME": -37.12792704,
      "RMB_LOAN_SEQUENTIAL": -51.68715244,
      "RMB_LOAN_ACCUMULATE": 108304.655917,
      "LOAN_ACCUMULATE_SAME": 7.75903222
    },
    {
      "REPORT_DATE": "2019-06-01 00:00:00",
      "TIME": "2019年06月份",
      "RMB_LOAN": 16736.89983,
      "RMB_LOAN_SAME": -0.30047669,
      "RMB_LOAN_SEQUENTIAL": 41.17462824,
      "RMB_LOAN_ACCUMULATE": 100218.583016,
      "LOAN_ACCUMULATE_SAME": 14.34579462
    },
    {
      "REPORT_DATE": "2019-05-01 00:00:00",
      "TIME": "2019年05月份",
      "RMB_LOAN": 11855.45876,
      "RMB_LOAN_SAME": 4.0300789,
      "RMB_LOAN_SEQUENTIAL": 35.75739077,
      "RMB_LOAN_ACCUMULATE": 83481.683186,
      "LOAN_ACCUMULATE_SAME": 17.81572757
    },
    {
      "REPORT_DATE": "2019-04-01 00:00:00",
      "TIME": "2019年04月份",
      "RMB_LOAN": 8732.827504,
      "RMB_LOAN_SAME": -20.51926011,
      "RMB_LOAN_SEQUENTIAL": -55.40925687,
      "RMB_LOAN_ACCUMULATE": 71626.224426,
      "LOAN_ACCUMULATE_SAME": 20.4578298
    },
    {
      "REPORT_DATE": "2019-03-01 00:00:00",
      "TIME": "2019年03月份",
      "RMB_LOAN": 19584.39553,
      "RMB_LOAN_SAME": 71.42350529,
      "RMB_LOAN_SEQUENTIAL": 156.31872143,
      "RMB_LOAN_ACCUMULATE": 62893.396922,
      "LOAN_ACCUMULATE_SAME": 29.74583538
    },
    {
      "REPORT_DATE": "2019-02-01 00:00:00",
      "TIME": "2019年02月份",
      "RMB_LOAN": 7640.641862,
      "RMB_LOAN_SAME": -25.0879703,
      "RMB_LOAN_SEQUENTIAL": -78.57865637,
      "RMB_LOAN_ACCUMULATE": 43309.001392,
      "LOAN_ACCUMULATE_SAME": 16.8942099
    },
    {
      "REPORT_DATE": "2019-01-01 00:00:00",
      "TIME": "2019年01月份",
      "RMB_LOAN": 35668.35953,
      "RMB_LOAN_SAME": 32.84179246,
      "RMB_LOAN_SEQUENTIAL": 284.29668051,
      "RMB_LOAN_ACCUMULATE": 35668.35953,
      "LOAN_ACCUMULATE_SAME": 32.84179246
    },
    {
      "REPORT_DATE": "2018-12-01 00:00:00",
      "TIME": "2018年12月份",
      "RMB_LOAN": 9281.464384,
      "RMB_LOAN_SAME": 60.87147054,
      "RMB_LOAN_SEQUENTIAL": -24.55522504,
      "RMB_LOAN_ACCUMULATE": 156712.410745,
      "LOAN_ACCUMULATE_SAME": 13.20501816
    },
    {
      "REPORT_DATE": "2018-11-01 00:00:00",
      "TIME": "2018年11月份",
      "RMB_LOAN": 12302.32894,
      "RMB_LOAN_SAME": 7.64641534,
      "RMB_LOAN_SEQUENTIAL": 72.27057953,
      "RMB_LOAN_ACCUMULATE": 147430.946361,
      "LOAN_ACCUMULATE_SAME": 11.13201091
    },
    {
      "REPORT_DATE": "2018-10-01 00:00:00",
      "TIME": "2018年10月份",
      "RMB_LOAN": 7141.282611,
      "RMB_LOAN_SAME": 7.6264382,
      "RMB_LOAN_SEQUENTIAL": -50.20373064,
      "RMB_LOAN_ACCUMULATE": 135128.617421,
      "LOAN_ACCUMULATE_SAME": 11.46058912
    },
    {
      "REPORT_DATE": "2018-09-01 00:00:00",
      "TIME": "2018年09月份",
      "RMB_LOAN": 14340.99924,
      "RMB_LOAN_SAME": 20.6662837,
      "RMB_LOAN_SEQUENTIAL": 9.14003537,
      "RMB_LOAN_ACCUMULATE": 127987.33481,
      "LOAN_ACCUMULATE_SAME": 11.68258501
    },
    {
      "REPORT_DATE": "2018-08-01 00:00:00",
      "TIME": "2018年08月份",
      "RMB_LOAN": 13139.99871,
      "RMB_LOAN_SAME": 14.5981459,
      "RMB_LOAN_SEQUENTIAL": 2.16813128,
      "RMB_LOAN_ACCUMULATE": 113646.33557,
      "LOAN_ACCUMULATE_SAME": 10.64310161
    },
    {
      "REPORT_DATE": "2018-07-01 00:00:00",
      "TIME": "2018年07月份",
      "RMB_LOAN": 12861.15205,
      "RMB_LOAN_SAME": 40.53507867,
      "RMB_LOAN_SEQUENTIAL": -23.38779932,
      "RMB_LOAN_ACCUMULATE": 100506.33686,
      "LOAN_ACCUMULATE_SAME": 10.14611485
    },
    {
      "REPORT_DATE": "2018-06-01 00:00:00",
      "TIME": "2018年06月份",
      "RMB_LOAN": 16787.34188,
      "RMB_LOAN_SAME": 15.97990156,
      "RMB_LOAN_SEQUENTIAL": 47.30669945,
      "RMB_LOAN_ACCUMULATE": 87645.18481,
      "LOAN_ACCUMULATE_SAME": 6.75856503
    },
    {
      "REPORT_DATE": "2018-05-01 00:00:00",
      "TIME": "2018年05月份",
      "RMB_LOAN": 11396.18357,
      "RMB_LOAN_SAME": -3.26115181,
      "RMB_LOAN_SEQUENTIAL": 3.72094281,
      "RMB_LOAN_ACCUMULATE": 70857.84293,
      "LOAN_ACCUMULATE_SAME": 4.78476439
    },
    {
      "REPORT_DATE": "2018-04-01 00:00:00",
      "TIME": "2018年04月份",
      "RMB_LOAN": 10987.35054,
      "RMB_LOAN_SAME": 1.68117457,
      "RMB_LOAN_SEQUENTIAL": -3.82699632,
      "RMB_LOAN_ACCUMULATE": 59461.65936,
      "LOAN_ACCUMULATE_SAME": 6.48212339
    },
    {
      "REPORT_DATE": "2018-03-01 00:00:00",
      "TIME": "2018年03月份",
      "RMB_LOAN": 11424.56835,
      "RMB_LOAN_SAME": -1.39381275,
      "RMB_LOAN_SEQUENTIAL": 12.0112183,
      "RMB_LOAN_ACCUMULATE": 48474.30882,
      "LOAN_ACCUMULATE_SAME": 7.63403056
    },
    {
      "REPORT_DATE": "2018-02-01 00:00:00",
      "TIME": "2018年02月份",
      "RMB_LOAN": 10199.48584,
      "RMB_LOAN_SAME": -1.1420837,
      "RMB_LOAN_SEQUENTIAL": -62.01344836,
      "RMB_LOAN_ACCUMULATE": 37049.74047,
      "LOAN_ACCUMULATE_SAME": 10.76098302
    },
    {
      "REPORT_DATE": "2018-01-01 00:00:00",
      "TIME": "2018年01月份",
      "RMB_LOAN": 26850.25463,
      "RMB_LOAN_SAME": 16.06978423,
      "RMB_LOAN_SEQUENTIAL": 365.38345331,
      "RMB_LOAN_ACCUMULATE": 26850.25463,
      "LOAN_ACCUMULATE_SAME": 16.06978423
    },
    {
      "REPORT_DATE": "2017-12-01 00:00:00",
      "TIME": "2017年12月份",
      "RMB_LOAN": 5769.490608,
      "RMB_LOAN_SAME": -41.97311036,
      "RMB_LOAN_SEQUENTIAL": -49.5164708,
      "RMB_LOAN_ACCUMULATE": 138432.388676,
      "LOAN_ACCUMULATE_SAME": 11.30478036
    },
    {
      "REPORT_DATE": "2017-11-01 00:00:00",
      "TIME": "2017年11月份",
      "RMB_LOAN": 11428.46132,
      "RMB_LOAN_SAME": 35.03612743,
      "RMB_LOAN_SEQUENTIAL": 72.23860936,
      "RMB_LOAN_ACCUMULATE": 132662.898068,
      "LOAN_ACCUMULATE_SAME": 15.93409719
    },
    {
      "REPORT_DATE": "2017-10-01 00:00:00",
      "TIME": "2017年10月份",
      "RMB_LOAN": 6635.249415,
      "RMB_LOAN_SAME": 10.39741165,
      "RMB_LOAN_SEQUENTIAL": -44.17049503,
      "RMB_LOAN_ACCUMULATE": 121234.436748,
      "LOAN_ACCUMULATE_SAME": 14.40846628
    },
    {
      "REPORT_DATE": "2017-09-01 00:00:00",
      "TIME": "2017年09月份",
      "RMB_LOAN": 11884.84372,
      "RMB_LOAN_SAME": -5.88546234,
      "RMB_LOAN_SEQUENTIAL": 3.65153641,
      "RMB_LOAN_ACCUMULATE": 114599.187333,
      "LOAN_ACCUMULATE_SAME": 14.64965008
    },
    {
      "REPORT_DATE": "2017-08-01 00:00:00",
      "TIME": "2017年08月份",
      "RMB_LOAN": 11466.15297,
      "RMB_LOAN_SAME": 43.88092191,
      "RMB_LOAN_SEQUENTIAL": 25.29178595,
      "RMB_LOAN_ACCUMULATE": 102714.343613,
      "LOAN_ACCUMULATE_SAME": 17.61913226
    },
    {
      "REPORT_DATE": "2017-07-01 00:00:00",
      "TIME": "2017年07月份",
      "RMB_LOAN": 9151.560003,
      "RMB_LOAN_SAME": 101.12332269,
      "RMB_LOAN_SEQUENTIAL": -36.7739672,
      "RMB_LOAN_ACCUMULATE": 91248.190643,
      "LOAN_ACCUMULATE_SAME": 14.98192565
    },
    {
      "REPORT_DATE": "2017-06-01 00:00:00",
      "TIME": "2017年06月份",
      "RMB_LOAN": 14474.35431,
      "RMB_LOAN_SAME": 10.14561976,
      "RMB_LOAN_SEQUENTIAL": 22.86853363,
      "RMB_LOAN_ACCUMULATE": 82096.63064,
      "LOAN_ACCUMULATE_SAME": 9.74237978
    },
    {
      "REPORT_DATE": "2017-05-01 00:00:00",
      "TIME": "2017年05月份",
      "RMB_LOAN": 11780.35896,
      "RMB_LOAN_SAME": 25.6669785,
      "RMB_LOAN_SEQUENTIAL": 9.01997998,
      "RMB_LOAN_ACCUMULATE": 67622.27633,
      "LOAN_ACCUMULATE_SAME": 9.65645074
    },
    {
      "REPORT_DATE": "2017-04-01 00:00:00",
      "TIME": "2017年04月份",
      "RMB_LOAN": 10805.68806,
      "RMB_LOAN_SAME": 91.52050855,
      "RMB_LOAN_SEQUENTIAL": -6.7354085,
      "RMB_LOAN_ACCUMULATE": 55841.91737,
      "LOAN_ACCUMULATE_SAME": 6.78634177
    },
    {
      "REPORT_DATE": "2017-03-01 00:00:00",
      "TIME": "2017年03月份",
      "RMB_LOAN": 11586.05628,
      "RMB_LOAN_SAME": -12.0640436,
      "RMB_LOAN_SEQUENTIAL": 12.29716869,
      "RMB_LOAN_ACCUMULATE": 45036.22931,
      "LOAN_ACCUMULATE_SAME": -3.46153876
    },
    {
      "REPORT_DATE": "2017-02-01 00:00:00",
      "TIME": "2017年02月份",
      "RMB_LOAN": 10317.31825,
      "RMB_LOAN_SAME": 27.28877533,
      "RMB_LOAN_SEQUENTIAL": -55.39971894,
      "RMB_LOAN_ACCUMULATE": 33450.17303,
      "LOAN_ACCUMULATE_SAME": -0.07569563
    },
    {
      "REPORT_DATE": "2017-01-01 00:00:00",
      "TIME": "2017年01月份",
      "RMB_LOAN": 23132.85478,
      "RMB_LOAN_SAME": -8.81832577,
      "RMB_LOAN_SEQUENTIAL": 132.6596406,
      "RMB_LOAN_ACCUMULATE": 23132.85478,
      "LOAN_ACCUMULATE_SAME": -8.81832577
    },
    {
      "REPORT_DATE": "2016-12-01 00:00:00",
      "TIME": "2016年12月份",
      "RMB_LOAN": 9942.78798,
      "RMB_LOAN_SAME": 19.46039351,
      "RMB_LOAN_SEQUENTIAL": 17.48174554,
      "RMB_LOAN_ACCUMULATE": 124372.365885,
      "LOAN_ACCUMULATE_SAME": 10.3639735
    },
    {
      "REPORT_DATE": "2016-11-01 00:00:00",
      "TIME": "2016年11月份",
      "RMB_LOAN": 8463.262045,
      "RMB_LOAN_SAME": -4.61675746,
      "RMB_LOAN_SEQUENTIAL": 40.81192212,
      "RMB_LOAN_ACCUMULATE": 114429.577905,
      "LOAN_ACCUMULATE_SAME": 9.63856973
    },
    {
      "REPORT_DATE": "2016-10-01 00:00:00",
      "TIME": "2016年10月份",
      "RMB_LOAN": 6010.330601,
      "RMB_LOAN_SAME": 7.83268881,
      "RMB_LOAN_SEQUENTIAL": -52.40497065,
      "RMB_LOAN_ACCUMULATE": 105966.31586,
      "LOAN_ACCUMULATE_SAME": 10.96307455
    },
    {
      "REPORT_DATE": "2016-09-01 00:00:00",
      "TIME": "2016年09月份",
      "RMB_LOAN": 12628.06365,
      "RMB_LOAN_SAME": 21.22268239,
      "RMB_LOAN_SEQUENTIAL": 58.46094541,
      "RMB_LOAN_ACCUMULATE": 99955.985259,
      "LOAN_ACCUMULATE_SAME": 11.15710693
    },
    {
      "REPORT_DATE": "2016-08-01 00:00:00",
      "TIME": "2016年08月份",
      "RMB_LOAN": 7969.196206,
      "RMB_LOAN_SAME": 2.74985559,
      "RMB_LOAN_SEQUENTIAL": 75.1385796,
      "RMB_LOAN_ACCUMULATE": 87327.921609,
      "LOAN_ACCUMULATE_SAME": 9.83826717
    },
    {
      "REPORT_DATE": "2016-07-01 00:00:00",
      "TIME": "2016年07月份",
      "RMB_LOAN": 4550.223157,
      "RMB_LOAN_SAME": -22.75278578,
      "RMB_LOAN_SEQUENTIAL": -65.37412731,
      "RMB_LOAN_ACCUMULATE": 79358.725403,
      "LOAN_ACCUMULATE_SAME": 10.60449926
    },
    {
      "REPORT_DATE": "2016-06-01 00:00:00",
      "TIME": "2016年06月份",
      "RMB_LOAN": 13141.10751,
      "RMB_LOAN_SAME": -0.74361458,
      "RMB_LOAN_SEQUENTIAL": 40.18276358,
      "RMB_LOAN_ACCUMULATE": 74808.502246,
      "LOAN_ACCUMULATE_SAME": 13.58797114
    },
    {
      "REPORT_DATE": "2016-05-01 00:00:00",
      "TIME": "2016年05月份",
      "RMB_LOAN": 9374.267688,
      "RMB_LOAN_SAME": 10.15355362,
      "RMB_LOAN_SEQUENTIAL": 66.14994852,
      "RMB_LOAN_ACCUMULATE": 61667.394736,
      "LOAN_ACCUMULATE_SAME": 17.19390009
    },
    {
      "REPORT_DATE": "2016-04-01 00:00:00",
      "TIME": "2016年04月份",
      "RMB_LOAN": 5642.052719,
      "RMB_LOAN_SAME": -29.86935526,
      "RMB_LOAN_SEQUENTIAL": -57.17789644,
      "RMB_LOAN_ACCUMULATE": 52293.127048,
      "LOAN_ACCUMULATE_SAME": 18.55220697
    },
    {
      "REPORT_DATE": "2016-03-01 00:00:00",
      "TIME": "2016年03月份",
      "RMB_LOAN": 13175.5618,
      "RMB_LOAN_SAME": 32.82001106,
      "RMB_LOAN_SEQUENTIAL": 62.5520397,
      "RMB_LOAN_ACCUMULATE": 46651.074329,
      "LOAN_ACCUMULATE_SAME": 29.35374129
    },
    {
      "REPORT_DATE": "2016-02-01 00:00:00",
      "TIME": "2016年02月份",
      "RMB_LOAN": 8105.442309,
      "RMB_LOAN_SAME": -29.12953229,
      "RMB_LOAN_SEQUENTIAL": -68.05116329,
      "RMB_LOAN_ACCUMULATE": 33475.512529,
      "LOAN_ACCUMULATE_SAME": 28.03857225
    },
    {
      "REPORT_DATE": "2016-01-01 00:00:00",
      "TIME": "2016年01月份",
      "RMB_LOAN": 25370.07022,
      "RMB_LOAN_SAME": 72.49299936,
      "RMB_LOAN_SEQUENTIAL": 204.81576978,
      "RMB_LOAN_ACCUMULATE": 25370.07022,
      "LOAN_ACCUMULATE_SAME": 72.49299936
    },
    {
      "REPORT_DATE": "2015-12-01 00:00:00",
      "TIME": "2015年12月份",
      "RMB_LOAN": 8323.083231,
      "RMB_LOAN_SAME": 19.36158369,
      "RMB_LOAN_SEQUENTIAL": -6.19661045,
      "RMB_LOAN_ACCUMULATE": 112692.903255,
      "LOAN_ACCUMULATE_SAME": 15.21260288
    },
    {
      "REPORT_DATE": "2015-11-01 00:00:00",
      "TIME": "2015年11月份",
      "RMB_LOAN": 8872.90243,
      "RMB_LOAN_SAME": 4.05655483,
      "RMB_LOAN_SEQUENTIAL": 59.19073177,
      "RMB_LOAN_ACCUMULATE": 104369.820024,
      "LOAN_ACCUMULATE_SAME": 14.89412156
    },
    {
      "REPORT_DATE": "2015-10-01 00:00:00",
      "TIME": "2015年10月份",
      "RMB_LOAN": 5573.755665,
      "RMB_LOAN_SAME": 1.65521913,
      "RMB_LOAN_SEQUENTIAL": -46.4949155,
      "RMB_LOAN_ACCUMULATE": 95496.917594,
      "LOAN_ACCUMULATE_SAME": 16.01681095
    },
    {
      "REPORT_DATE": "2015-09-01 00:00:00",
      "TIME": "2015年09月份",
      "RMB_LOAN": 10417.24486,
      "RMB_LOAN_SAME": 21.52642161,
      "RMB_LOAN_SEQUENTIAL": 34.31347119,
      "RMB_LOAN_ACCUMULATE": 89923.161929,
      "LOAN_ACCUMULATE_SAME": 17.041731
    },
    {
      "REPORT_DATE": "2015-08-01 00:00:00",
      "TIME": "2015年08月份",
      "RMB_LOAN": 7755.919617,
      "RMB_LOAN_SAME": 10.40454971,
      "RMB_LOAN_SEQUENTIAL": 31.66896732,
      "RMB_LOAN_ACCUMULATE": 79505.917069,
      "LOAN_ACCUMULATE_SAME": 16.47853302
    },
    {
      "REPORT_DATE": "2015-07-01 00:00:00",
      "TIME": "2015年07月份",
      "RMB_LOAN": 5890.468935,
      "RMB_LOAN_SAME": 52.91975428,
      "RMB_LOAN_SEQUENTIAL": -55.50857076,
      "RMB_LOAN_ACCUMULATE": 71749.997452,
      "LOAN_ACCUMULATE_SAME": 17.17537513
    },
    {
      "REPORT_DATE": "2015-06-01 00:00:00",
      "TIME": "2015年06月份",
      "RMB_LOAN": 13239.5588,
      "RMB_LOAN_SAME": 22.66801445,
      "RMB_LOAN_SEQUENTIAL": 55.57316036,
      "RMB_LOAN_ACCUMULATE": 65859.528517,
      "LOAN_ACCUMULATE_SAME": 14.77584656
    },
    {
      "REPORT_DATE": "2015-05-01 00:00:00",
      "TIME": "2015年05月份",
      "RMB_LOAN": 8510.181814,
      "RMB_LOAN_SAME": -2.27168335,
      "RMB_LOAN_SEQUENTIAL": 5.78145352,
      "RMB_LOAN_ACCUMULATE": 52619.969717,
      "LOAN_ACCUMULATE_SAME": 12.94747514
    },
    {
      "REPORT_DATE": "2015-04-01 00:00:00",
      "TIME": "2015年04月份",
      "RMB_LOAN": 8045.060387,
      "RMB_LOAN_SAME": 3.87424644,
      "RMB_LOAN_SEQUENTIAL": -18.89947269,
      "RMB_LOAN_ACCUMULATE": 44109.787903,
      "LOAN_ACCUMULATE_SAME": 16.44611379
    },
    {
      "REPORT_DATE": "2015-03-01 00:00:00",
      "TIME": "2015年03月份",
      "RMB_LOAN": 9919.861996,
      "RMB_LOAN_SAME": -5.49812331,
      "RMB_LOAN_SEQUENTIAL": -13.26503447,
      "RMB_LOAN_ACCUMULATE": 36064.727516,
      "LOAN_ACCUMULATE_SAME": 19.67721094
    },
    {
      "REPORT_DATE": "2015-02-01 00:00:00",
      "TIME": "2015年02月份",
      "RMB_LOAN": 11436.98154,
      "RMB_LOAN_SAME": 77.37254249,
      "RMB_LOAN_SEQUENTIAL": -22.23910961,
      "RMB_LOAN_ACCUMULATE": 26144.86552,
      "LOAN_ACCUMULATE_SAME": 33.13405398
    },
    {
      "REPORT_DATE": "2015-01-01 00:00:00",
      "TIME": "2015年01月份",
      "RMB_LOAN": 14707.88398,
      "RMB_LOAN_SAME": 11.50783912,
      "RMB_LOAN_SEQUENTIAL": 110.92620077,
      "RMB_LOAN_ACCUMULATE": 14707.88398,
      "LOAN_ACCUMULATE_SAME": 11.50783912
    },
    {
      "REPORT_DATE": "2014-12-01 00:00:00",
      "TIME": "2014年12月份",
      "RMB_LOAN": 6973,
      "RMB_LOAN_SAME": 44.51813472,
      "RMB_LOAN_SEQUENTIAL": -18.22446347,
      "RMB_LOAN_ACCUMULATE": 97813,
      "LOAN_ACCUMULATE_SAME": 10.00483597
    },
    {
      "REPORT_DATE": "2014-11-01 00:00:00",
      "TIME": "2014年11月份",
      "RMB_LOAN": 8527,
      "RMB_LOAN_SAME": 36.5193724,
      "RMB_LOAN_SEQUENTIAL": 55.51705271,
      "RMB_LOAN_ACCUMULATE": 90840,
      "LOAN_ACCUMULATE_SAME": 8.02454455
    },
    {
      "REPORT_DATE": "2014-10-01 00:00:00",
      "TIME": "2014年10月份",
      "RMB_LOAN": 5483,
      "RMB_LOAN_SAME": 8.35968379,
      "RMB_LOAN_SEQUENTIAL": -36.03593094,
      "RMB_LOAN_ACCUMULATE": 82313,
      "LOAN_ACCUMULATE_SAME": 5.73825245
    },
    {
      "REPORT_DATE": "2014-09-01 00:00:00",
      "TIME": "2014年09月份",
      "RMB_LOAN": 8572,
      "RMB_LOAN_SAME": 8.91994917,
      "RMB_LOAN_SEQUENTIAL": 22.02135231,
      "RMB_LOAN_ACCUMULATE": 76830,
      "LOAN_ACCUMULATE_SAME": 5.55601352
    },
    {
      "REPORT_DATE": "2014-08-01 00:00:00",
      "TIME": "2014年08月份",
      "RMB_LOAN": 7025,
      "RMB_LOAN_SAME": -1.44500561,
      "RMB_LOAN_SEQUENTIAL": 82.37279335,
      "RMB_LOAN_ACCUMULATE": 68258,
      "LOAN_ACCUMULATE_SAME": 5.14819151
    },
    {
      "REPORT_DATE": "2014-07-01 00:00:00",
      "TIME": "2014年07月份",
      "RMB_LOAN": 3852,
      "RMB_LOAN_SAME": -44.94783479,
      "RMB_LOAN_SEQUENTIAL": -64.31020106,
      "RMB_LOAN_ACCUMULATE": 61233,
      "LOAN_ACCUMULATE_SAME": 5.96144528
    },
    {
      "REPORT_DATE": "2014-06-01 00:00:00",
      "TIME": "2014年06月份",
      "RMB_LOAN": 10793,
      "RMB_LOAN_SAME": 25.09272137,
      "RMB_LOAN_SEQUENTIAL": 23.94350023,
      "RMB_LOAN_ACCUMULATE": 57381,
      "LOAN_ACCUMULATE_SAME": 12.97473962
    },
    {
      "REPORT_DATE": "2014-05-01 00:00:00",
      "TIME": "2014年05月份",
      "RMB_LOAN": 8708,
      "RMB_LOAN_SAME": 30.08664476,
      "RMB_LOAN_SEQUENTIAL": 12.43382828,
      "RMB_LOAN_ACCUMULATE": 46588,
      "LOAN_ACCUMULATE_SAME": 10.49498375
    },
    {
      "REPORT_DATE": "2014-04-01 00:00:00",
      "TIME": "2014年04月份",
      "RMB_LOAN": 7745,
      "RMB_LOAN_SAME": -2.24662375,
      "RMB_LOAN_SEQUENTIAL": -26.21701439,
      "RMB_LOAN_ACCUMULATE": 37880,
      "LOAN_ACCUMULATE_SAME": 6.79748513
    },
    {
      "REPORT_DATE": "2014-03-01 00:00:00",
      "TIME": "2014年03月份",
      "RMB_LOAN": 10497,
      "RMB_LOAN_SAME": -1.20470588,
      "RMB_LOAN_SEQUENTIAL": 62.79466501,
      "RMB_LOAN_ACCUMULATE": 30135,
      "LOAN_ACCUMULATE_SAME": 9.39882379
    },
    {
      "REPORT_DATE": "2014-02-01 00:00:00",
      "TIME": "2014年02月份",
      "RMB_LOAN": 6448,
      "RMB_LOAN_SAME": 4,
      "RMB_LOAN_SEQUENTIAL": -51.11448067,
      "RMB_LOAN_ACCUMULATE": 19638,
      "LOAN_ACCUMULATE_SAME": 16.05697063
    },
    {
      "REPORT_DATE": "2014-01-01 00:00:00",
      "TIME": "2014年01月份",
      "RMB_LOAN": 13190,
      "RMB_LOAN_SAME": 23.02956814,
      "RMB_LOAN_SEQUENTIAL": 173.36787565,
      "RMB_LOAN_ACCUMULATE": 13190,
      "LOAN_ACCUMULATE_SAME": 23.02956814
    },
    {
      "REPORT_DATE": "2013-12-01 00:00:00",
      "TIME": "2013年12月份",
      "RMB_LOAN": 4825,
      "RMB_LOAN_SAME": 6.13539577,
      "RMB_LOAN_SEQUENTIAL": -22.75056036,
      "RMB_LOAN_ACCUMULATE": 88917,
      "LOAN_ACCUMULATE_SAME": 8.38546888
    },
    {
      "REPORT_DATE": "2013-11-01 00:00:00",
      "TIME": "2013年11月份",
      "RMB_LOAN": 6246,
      "RMB_LOAN_SAME": 19.64669171,
      "RMB_LOAN_SEQUENTIAL": 23.43873518,
      "RMB_LOAN_ACCUMULATE": 84092,
      "LOAN_ACCUMULATE_SAME": 8.51747033
    },
    {
      "REPORT_DATE": "2013-10-01 00:00:00",
      "TIME": "2013年10月份",
      "RMB_LOAN": 5060,
      "RMB_LOAN_SAME": 0.12446302,
      "RMB_LOAN_SEQUENTIAL": -35.70520966,
      "RMB_LOAN_ACCUMULATE": 77846,
      "LOAN_ACCUMULATE_SAME": 7.71357371
    },
    {
      "REPORT_DATE": "2013-09-01 00:00:00",
      "TIME": "2013年09月份",
      "RMB_LOAN": 7870,
      "RMB_LOAN_SAME": 26.40072725,
      "RMB_LOAN_SEQUENTIAL": 10.40965208,
      "RMB_LOAN_ACCUMULATE": 72786,
      "LOAN_ACCUMULATE_SAME": 8.28415598
    },
    {
      "REPORT_DATE": "2013-08-01 00:00:00",
      "TIME": "2013年08月份",
      "RMB_LOAN": 7128,
      "RMB_LOAN_SAME": 1.25791077,
      "RMB_LOAN_SEQUENTIAL": 1.87223096,
      "RMB_LOAN_ACCUMULATE": 64916,
      "LOAN_ACCUMULATE_SAME": 6.43474748
    },
    {
      "REPORT_DATE": "2013-07-01 00:00:00",
      "TIME": "2013年07月份",
      "RMB_LOAN": 6997,
      "RMB_LOAN_SAME": 29.54504639,
      "RMB_LOAN_SEQUENTIAL": -18.90356977,
      "RMB_LOAN_ACCUMULATE": 57788,
      "LOAN_ACCUMULATE_SAME": 7.1102024
    },
    {
      "REPORT_DATE": "2013-06-01 00:00:00",
      "TIME": "2013年06月份",
      "RMB_LOAN": 8628,
      "RMB_LOAN_SAME": -6.19873301,
      "RMB_LOAN_SEQUENTIAL": 28.89154467,
      "RMB_LOAN_ACCUMULATE": 50791,
      "LOAN_ACCUMULATE_SAME": 4.6143516
    },
    {
      "REPORT_DATE": "2013-05-01 00:00:00",
      "TIME": "2013年05月份",
      "RMB_LOAN": 6694,
      "RMB_LOAN_SAME": -15.61106965,
      "RMB_LOAN_SEQUENTIAL": -15.51180109,
      "RMB_LOAN_ACCUMULATE": 42163,
      "LOAN_ACCUMULATE_SAME": 7.14177716
    },
    {
      "REPORT_DATE": "2013-04-01 00:00:00",
      "TIME": "2013年04月份",
      "RMB_LOAN": 7923,
      "RMB_LOAN_SAME": 16.21067824,
      "RMB_LOAN_SEQUENTIAL": -25.43058824,
      "RMB_LOAN_ACCUMULATE": 35469,
      "LOAN_ACCUMULATE_SAME": 12.88594188
    },
    {
      "REPORT_DATE": "2013-03-01 00:00:00",
      "TIME": "2013年03月份",
      "RMB_LOAN": 10625,
      "RMB_LOAN_SAME": 5.04804032,
      "RMB_LOAN_SEQUENTIAL": 71.37096774,
      "RMB_LOAN_ACCUMULATE": 27546,
      "LOAN_ACCUMULATE_SAME": 11.96459535
    },
    {
      "REPORT_DATE": "2013-02-01 00:00:00",
      "TIME": "2013年02月份",
      "RMB_LOAN": 6200,
      "RMB_LOAN_SAME": -12.76206557,
      "RMB_LOAN_SEQUENTIAL": -42.16957373,
      "RMB_LOAN_ACCUMULATE": 16921,
      "LOAN_ACCUMULATE_SAME": 16.79320817
    },
    {
      "REPORT_DATE": "2013-01-01 00:00:00",
      "TIME": "2013年01月份",
      "RMB_LOAN": 10721,
      "RMB_LOAN_SAME": 45.25132096,
      "RMB_LOAN_SEQUENTIAL": 135.82954985,
      "RMB_LOAN_ACCUMULATE": 10721,
      "LOAN_ACCUMULATE_SAME": 45.25132096
    },
    {
      "REPORT_DATE": "2012-12-01 00:00:00",
      "TIME": "2012年12月份",
      "RMB_LOAN": 4546.08,
      "RMB_LOAN_SAME": -29.0340306,
      "RMB_LOAN_SEQUENTIAL": -12.91651741,
      "RMB_LOAN_ACCUMULATE": 82037.75,
      "LOAN_ACCUMULATE_SAME": 9.80091013
    },
    {
      "REPORT_DATE": "2012-11-01 00:00:00",
      "TIME": "2012年11月份",
      "RMB_LOAN": 5220.37,
      "RMB_LOAN_SAME": -7.25937111,
      "RMB_LOAN_SEQUENTIAL": 3.2977753,
      "RMB_LOAN_ACCUMULATE": 77491.67,
      "LOAN_ACCUMULATE_SAME": 13.44284062
    },
    {
      "REPORT_DATE": "2012-10-01 00:00:00",
      "TIME": "2012年10月份",
      "RMB_LOAN": 5053.71,
      "RMB_LOAN_SAME": -13.87678937,
      "RMB_LOAN_SEQUENTIAL": -18.83194164,
      "RMB_LOAN_ACCUMULATE": 72271.3,
      "LOAN_ACCUMULATE_SAME": 15.30201021
    },
    {
      "REPORT_DATE": "2012-09-01 00:00:00",
      "TIME": "2012年09月份",
      "RMB_LOAN": 6226.23,
      "RMB_LOAN_SAME": 32.67057319,
      "RMB_LOAN_SEQUENTIAL": -11.55232298,
      "RMB_LOAN_ACCUMULATE": 67217.59,
      "LOAN_ACCUMULATE_SAME": 18.31583116
    },
    {
      "REPORT_DATE": "2012-08-01 00:00:00",
      "TIME": "2012年08月份",
      "RMB_LOAN": 7039.45,
      "RMB_LOAN_SAME": 28.36342086,
      "RMB_LOAN_SEQUENTIAL": 30.33098139,
      "RMB_LOAN_ACCUMULATE": 60991.36,
      "LOAN_ACCUMULATE_SAME": 17.02327366
    },
    {
      "REPORT_DATE": "2012-07-01 00:00:00",
      "TIME": "2012年07月份",
      "RMB_LOAN": 5401.21,
      "RMB_LOAN_SAME": 9.87001627,
      "RMB_LOAN_SEQUENTIAL": -41.27951538,
      "RMB_LOAN_ACCUMULATE": 53951.91,
      "LOAN_ACCUMULATE_SAME": 15.68973947
    },
    {
      "REPORT_DATE": "2012-06-01 00:00:00",
      "TIME": "2012年06月份",
      "RMB_LOAN": 9198.17,
      "RMB_LOAN_SAME": 45.10443288,
      "RMB_LOAN_SEQUENTIAL": 15.95813079,
      "RMB_LOAN_ACCUMULATE": 48550.7,
      "LOAN_ACCUMULATE_SAME": 16.37551236
    },
    {
      "REPORT_DATE": "2012-05-01 00:00:00",
      "TIME": "2012年05月份",
      "RMB_LOAN": 7932.32,
      "RMB_LOAN_SAME": 43.80565627,
      "RMB_LOAN_SEQUENTIAL": 16.34737943,
      "RMB_LOAN_ACCUMULATE": 39352.53,
      "LOAN_ACCUMULATE_SAME": 11.22817976
    },
    {
      "REPORT_DATE": "2012-04-01 00:00:00",
      "TIME": "2012年04月份",
      "RMB_LOAN": 6817.79,
      "RMB_LOAN_SAME": -8.2397039,
      "RMB_LOAN_SEQUENTIAL": -32.5933667,
      "RMB_LOAN_ACCUMULATE": 31420.21,
      "LOAN_ACCUMULATE_SAME": 5.21098982
    },
    {
      "REPORT_DATE": "2012-03-01 00:00:00",
      "TIME": "2012年03月份",
      "RMB_LOAN": 10114.42,
      "RMB_LOAN_SAME": 48.87282897,
      "RMB_LOAN_SEQUENTIAL": 42.31630787,
      "RMB_LOAN_ACCUMULATE": 24602.42,
      "LOAN_ACCUMULATE_SAME": 9.66577516
    },
    {
      "REPORT_DATE": "2012-02-01 00:00:00",
      "TIME": "2012年02月份",
      "RMB_LOAN": 7107,
      "RMB_LOAN_SAME": 32.17407476,
      "RMB_LOAN_SEQUENTIAL": -3.71223411,
      "RMB_LOAN_ACCUMULATE": 14488,
      "LOAN_ACCUMULATE_SAME": -7.3657289
    },
    {
      "REPORT_DATE": "2012-01-01 00:00:00",
      "TIME": "2012年01月份",
      "RMB_LOAN": 7381,
      "RMB_LOAN_SAME": -28.08145766,
      "RMB_LOAN_SEQUENTIAL": 15.22010615,
      "RMB_LOAN_ACCUMULATE": 7381,
      "LOAN_ACCUMULATE_SAME": -28.08145766
    },
    {
      "REPORT_DATE": "2011-12-01 00:00:00",
      "TIME": "2011年12月份",
      "RMB_LOAN": 6406,
      "RMB_LOAN_SAME": 33.26399001,
      "RMB_LOAN_SEQUENTIAL": 13.8035175,
      "RMB_LOAN_ACCUMULATE": 74715,
      "LOAN_ACCUMULATE_SAME": -5.9597231
    },
    {
      "REPORT_DATE": "2011-11-01 00:00:00",
      "TIME": "2011年11月份",
      "RMB_LOAN": 5629,
      "RMB_LOAN_SAME": -1.0546669,
      "RMB_LOAN_SEQUENTIAL": -4.07293797,
      "RMB_LOAN_ACCUMULATE": 68309,
      "LOAN_ACCUMULATE_SAME": -8.48572539
    },
    {
      "REPORT_DATE": "2011-10-01 00:00:00",
      "TIME": "2011年10月份",
      "RMB_LOAN": 5868,
      "RMB_LOAN_SAME": -0.15313936,
      "RMB_LOAN_SEQUENTIAL": 25.03728958,
      "RMB_LOAN_ACCUMULATE": 62680,
      "LOAN_ACCUMULATE_SAME": -9.0988195
    },
    {
      "REPORT_DATE": "2011-09-01 00:00:00",
      "TIME": "2011年09月份",
      "RMB_LOAN": 4693,
      "RMB_LOAN_SAME": -21.83544304,
      "RMB_LOAN_SEQUENTIAL": -14.42377826,
      "RMB_LOAN_ACCUMULATE": 56812,
      "LOAN_ACCUMULATE_SAME": -9.93230496
    },
    {
      "REPORT_DATE": "2011-08-01 00:00:00",
      "TIME": "2011年08月份",
      "RMB_LOAN": 5484,
      "RMB_LOAN_SAME": 0.69775982,
      "RMB_LOAN_SEQUENTIAL": 11.55410903,
      "RMB_LOAN_ACCUMULATE": 52119,
      "LOAN_ACCUMULATE_SAME": -8.68011144
    },
    {
      "REPORT_DATE": "2011-07-01 00:00:00",
      "TIME": "2011年07月份",
      "RMB_LOAN": 4916,
      "RMB_LOAN_SAME": -7.71541205,
      "RMB_LOAN_SEQUENTIAL": -22.4483357,
      "RMB_LOAN_ACCUMULATE": 46635,
      "LOAN_ACCUMULATE_SAME": -9.66935906
    },
    {
      "REPORT_DATE": "2011-06-01 00:00:00",
      "TIME": "2011年06月份",
      "RMB_LOAN": 6339,
      "RMB_LOAN_SAME": 5.17670483,
      "RMB_LOAN_SEQUENTIAL": 14.92023205,
      "RMB_LOAN_ACCUMULATE": 41719,
      "LOAN_ACCUMULATE_SAME": -9.89416847
    },
    {
      "REPORT_DATE": "2011-05-01 00:00:00",
      "TIME": "2011年05月份",
      "RMB_LOAN": 5516,
      "RMB_LOAN_SAME": -15.04697366,
      "RMB_LOAN_SEQUENTIAL": -25.76043069,
      "RMB_LOAN_ACCUMULATE": 35380,
      "LOAN_ACCUMULATE_SAME": -12.14957912
    },
    {
      "REPORT_DATE": "2011-04-01 00:00:00",
      "TIME": "2011年04月份",
      "RMB_LOAN": 7430,
      "RMB_LOAN_SAME": -4.00516796,
      "RMB_LOAN_SEQUENTIAL": 9.36120106,
      "RMB_LOAN_ACCUMULATE": 29864,
      "LOAN_ACCUMULATE_SAME": -11.59265838
    },
    {
      "REPORT_DATE": "2011-03-01 00:00:00",
      "TIME": "2011年03月份",
      "RMB_LOAN": 6794,
      "RMB_LOAN_SAME": 33.03309183,
      "RMB_LOAN_SEQUENTIAL": 26.35298494,
      "RMB_LOAN_ACCUMULATE": 22434,
      "LOAN_ACCUMULATE_SAME": -13.84792627
    },
    {
      "REPORT_DATE": "2011-02-01 00:00:00",
      "TIME": "2011年02月份",
      "RMB_LOAN": 5377,
      "RMB_LOAN_SAME": -23.17473925,
      "RMB_LOAN_SEQUENTIAL": -47.60791192,
      "RMB_LOAN_ACCUMULATE": 15640,
      "LOAN_ACCUMULATE_SAME": -25.28543448
    },
    {
      "REPORT_DATE": "2011-01-01 00:00:00",
      "TIME": "2011年01月份",
      "RMB_LOAN": 10263,
      "RMB_LOAN_SAME": -26.3456294,
      "RMB_LOAN_SEQUENTIAL": 113.50114416,
      "RMB_LOAN_ACCUMULATE": 10263,
      "LOAN_ACCUMULATE_SAME": -26.3456294
    },
    {
      "REPORT_DATE": "2010-12-01 00:00:00",
      "TIME": "2010年12月份",
      "RMB_LOAN": 4807,
      "RMB_LOAN_SAME": 26.5,
      "RMB_LOAN_SEQUENTIAL": -15.50360345,
      "RMB_LOAN_ACCUMULATE": 79450,
      "LOAN_ACCUMULATE_SAME": -17.19041514
    },
    {
      "REPORT_DATE": "2010-11-01 00:00:00",
      "TIME": "2010年11月份",
      "RMB_LOAN": 5689,
      "RMB_LOAN_SAME": 92.97829037,
      "RMB_LOAN_SEQUENTIAL": -3.19891101,
      "RMB_LOAN_ACCUMULATE": 74643,
      "LOAN_ACCUMULATE_SAME": -18.99221862
    },
    {
      "REPORT_DATE": "2010-10-01 00:00:00",
      "TIME": "2010年10月份",
      "RMB_LOAN": 5877,
      "RMB_LOAN_SAME": 132.29249012,
      "RMB_LOAN_SEQUENTIAL": -2.1152565,
      "RMB_LOAN_ACCUMULATE": 68954,
      "LOAN_ACCUMULATE_SAME": -22.69297606
    },
    {
      "REPORT_DATE": "2010-09-01 00:00:00",
      "TIME": "2010年09月份",
      "RMB_LOAN": 6004,
      "RMB_LOAN_SAME": 16.19895491,
      "RMB_LOAN_SEQUENTIAL": 10.24605215,
      "RMB_LOAN_ACCUMULATE": 63077,
      "LOAN_ACCUMULATE_SAME": -27.21744649
    },
    {
      "REPORT_DATE": "2010-08-01 00:00:00",
      "TIME": "2010年08月份",
      "RMB_LOAN": 5446,
      "RMB_LOAN_SAME": 32.69980507,
      "RMB_LOAN_SEQUENTIAL": 2.23390276,
      "RMB_LOAN_ACCUMULATE": 57073,
      "LOAN_ACCUMULATE_SAME": -29.97006061
    },
    {
      "REPORT_DATE": "2010-07-01 00:00:00",
      "TIME": "2010年07月份",
      "RMB_LOAN": 5327,
      "RMB_LOAN_SAME": 44.32403143,
      "RMB_LOAN_SEQUENTIAL": -11.61440186,
      "RMB_LOAN_ACCUMULATE": 51627,
      "LOAN_ACCUMULATE_SAME": -33.29327855
    },
    {
      "REPORT_DATE": "2010-06-01 00:00:00",
      "TIME": "2010年06月份",
      "RMB_LOAN": 6027,
      "RMB_LOAN_SAME": -60.61813905,
      "RMB_LOAN_SEQUENTIAL": -7.1769598,
      "RMB_LOAN_ACCUMULATE": 46300,
      "LOAN_ACCUMULATE_SAME": -37.18030474
    },
    {
      "REPORT_DATE": "2010-05-01 00:00:00",
      "TIME": "2010年05月份",
      "RMB_LOAN": 6493,
      "RMB_LOAN_SAME": -2.63907632,
      "RMB_LOAN_SEQUENTIAL": -16.11111111,
      "RMB_LOAN_ACCUMULATE": 40273,
      "LOAN_ACCUMULATE_SAME": -31.03820271
    },
    {
      "REPORT_DATE": "2010-04-01 00:00:00",
      "TIME": "2010年04月份",
      "RMB_LOAN": 7740,
      "RMB_LOAN_SAME": 30.78742819,
      "RMB_LOAN_SEQUENTIAL": 51.5566869,
      "RMB_LOAN_ACCUMULATE": 33780,
      "LOAN_ACCUMULATE_SAME": -34.69940073
    },
    {
      "REPORT_DATE": "2010-03-01 00:00:00",
      "TIME": "2010年03月份",
      "RMB_LOAN": 5107,
      "RMB_LOAN_SAME": -73.00739958,
      "RMB_LOAN_SEQUENTIAL": -27.0324332,
      "RMB_LOAN_ACCUMULATE": 26040,
      "LOAN_ACCUMULATE_SAME": -43.15899764
    },
    {
      "REPORT_DATE": "2010-02-01 00:00:00",
      "TIME": "2010年02月份",
      "RMB_LOAN": 6999,
      "RMB_LOAN_SAME": -34.68035464,
      "RMB_LOAN_SEQUENTIAL": -49.77034592,
      "RMB_LOAN_ACCUMULATE": 20933,
      "LOAN_ACCUMULATE_SAME": -22.1590064
    },
    {
      "REPORT_DATE": "2010-01-01 00:00:00",
      "TIME": "2010年01月份",
      "RMB_LOAN": 13934,
      "RMB_LOAN_SAME": -13.86536441,
      "RMB_LOAN_SEQUENTIAL": 266.68421053,
      "RMB_LOAN_ACCUMULATE": 13934,
      "LOAN_ACCUMULATE_SAME": -13.86536441
    },
    {
      "REPORT_DATE": "2009-12-01 00:00:00",
      "TIME": "2009年12月份",
      "RMB_LOAN": 3800,
      "RMB_LOAN_SAME": -50.29431001,
      "RMB_LOAN_SEQUENTIAL": 28.9009498,
      "RMB_LOAN_ACCUMULATE": 95943,
      "LOAN_ACCUMULATE_SAME": 95.63435423
    },
    {
      "REPORT_DATE": "2009-11-01 00:00:00",
      "TIME": "2009年11月份",
      "RMB_LOAN": 2948,
      "RMB_LOAN_SAME": -38.2617801,
      "RMB_LOAN_SEQUENTIAL": 16.52173913,
      "RMB_LOAN_ACCUMULATE": 92143,
      "LOAN_ACCUMULATE_SAME": 122.58376211
    },
    {
      "REPORT_DATE": "2009-10-01 00:00:00",
      "TIME": "2009年10月份",
      "RMB_LOAN": 2530,
      "RMB_LOAN_SAME": 39.08741067,
      "RMB_LOAN_SEQUENTIAL": -51.03541707,
      "RMB_LOAN_ACCUMULATE": 89195,
      "LOAN_ACCUMULATE_SAME": 143.55578614
    },
    {
      "REPORT_DATE": "2009-09-01 00:00:00",
      "TIME": "2009年09月份",
      "RMB_LOAN": 5167,
      "RMB_LOAN_SAME": 37.9706275,
      "RMB_LOAN_SEQUENTIAL": 25.90155945,
      "RMB_LOAN_ACCUMULATE": 86665,
      "LOAN_ACCUMULATE_SAME": 149.01588943
    },
    {
      "REPORT_DATE": "2009-08-01 00:00:00",
      "TIME": "2009年08月份",
      "RMB_LOAN": 4104,
      "RMB_LOAN_SAME": 51.16022099,
      "RMB_LOAN_SEQUENTIAL": 11.18937957,
      "RMB_LOAN_ACCUMULATE": 81498,
      "LOAN_ACCUMULATE_SAME": 162.40582137
    },
    {
      "REPORT_DATE": "2009-07-01 00:00:00",
      "TIME": "2009年07月份",
      "RMB_LOAN": 3691,
      "RMB_LOAN_SAME": -3.32634887,
      "RMB_LOAN_SEQUENTIAL": -75.88212232,
      "RMB_LOAN_ACCUMULATE": 77394,
      "LOAN_ACCUMULATE_SAME": 173.06213174
    },
    {
      "REPORT_DATE": "2009-06-01 00:00:00",
      "TIME": "2009年06月份",
      "RMB_LOAN": 15304,
      "RMB_LOAN_SAME": 360.40914561,
      "RMB_LOAN_SEQUENTIAL": 129.47968211,
      "RMB_LOAN_ACCUMULATE": 73703,
      "LOAN_ACCUMULATE_SAME": 200.52191641
    },
    {
      "REPORT_DATE": "2009-05-01 00:00:00",
      "TIME": "2009年05月份",
      "RMB_LOAN": 6669,
      "RMB_LOAN_SAME": 109.3877551,
      "RMB_LOAN_SEQUENTIAL": 12.69009801,
      "RMB_LOAN_ACCUMULATE": 58399,
      "LOAN_ACCUMULATE_SAME": 175.45398802
    },
    {
      "REPORT_DATE": "2009-04-01 00:00:00",
      "TIME": "2009年04月份",
      "RMB_LOAN": 5918,
      "RMB_LOAN_SAME": 26.18336887,
      "RMB_LOAN_SEQUENTIAL": -68.72093023,
      "RMB_LOAN_ACCUMULATE": 51730,
      "LOAN_ACCUMULATE_SAME": 187.13365897
    },
    {
      "REPORT_DATE": "2009-03-01 00:00:00",
      "TIME": "2009年03月份",
      "RMB_LOAN": 18920,
      "RMB_LOAN_SAME": 567.60762174,
      "RMB_LOAN_SEQUENTIAL": 76.57489501,
      "RMB_LOAN_ACCUMULATE": 45812,
      "LOAN_ACCUMULATE_SAME": 243.77907849
    },
    {
      "REPORT_DATE": "2009-02-01 00:00:00",
      "TIME": "2009年02月份",
      "RMB_LOAN": 10715,
      "RMB_LOAN_SAME": 340.22185703,
      "RMB_LOAN_SEQUENTIAL": -33.76398591,
      "RMB_LOAN_ACCUMULATE": 26892,
      "LOAN_ACCUMULATE_SAME": 156.3095692
    },
    {
      "REPORT_DATE": "2009-01-01 00:00:00",
      "TIME": "2009年01月份",
      "RMB_LOAN": 16177,
      "RMB_LOAN_SAME": 100.75701167,
      "RMB_LOAN_SEQUENTIAL": 111.60235448,
      "RMB_LOAN_ACCUMULATE": 16177,
      "LOAN_ACCUMULATE_SAME": 100.75701167
    },
    {
      "REPORT_DATE": "2008-12-01 00:00:00",
      "TIME": "2008年12月份",
      "RMB_LOAN": 7645,
      "RMB_LOAN_SAME": 1476.28865979,
      "RMB_LOAN_SEQUENTIAL": 60.10471204,
      "RMB_LOAN_ACCUMULATE": 49042,
      "LOAN_ACCUMULATE_SAME": 35.0126638
    },
    {
      "REPORT_DATE": "2008-11-01 00:00:00",
      "TIME": "2008年11月份",
      "RMB_LOAN": 4775,
      "RMB_LOAN_SAME": 446.33867277,
      "RMB_LOAN_SEQUENTIAL": 162.50687191,
      "RMB_LOAN_ACCUMULATE": 41397,
      "LOAN_ACCUMULATE_SAME": 15.50824521
    },
    {
      "REPORT_DATE": "2008-10-01 00:00:00",
      "TIME": "2008年10月份",
      "RMB_LOAN": 1819,
      "RMB_LOAN_SAME": 33.65172667,
      "RMB_LOAN_SEQUENTIAL": -51.42857143,
      "RMB_LOAN_ACCUMULATE": 36622,
      "LOAN_ACCUMULATE_SAME": 4.73902474
    },
    {
      "REPORT_DATE": "2008-09-01 00:00:00",
      "TIME": "2008年09月份",
      "RMB_LOAN": 3745,
      "RMB_LOAN_SAME": 32.09876543,
      "RMB_LOAN_SEQUENTIAL": 37.9373849,
      "RMB_LOAN_ACCUMULATE": 34803,
      "LOAN_ACCUMULATE_SAME": 3.56802762
    },
    {
      "REPORT_DATE": "2008-08-01 00:00:00",
      "TIME": "2008年08月份",
      "RMB_LOAN": 2715,
      "RMB_LOAN_SAME": -10.36645758,
      "RMB_LOAN_SEQUENTIAL": -28.88947093,
      "RMB_LOAN_ACCUMULATE": 31058,
      "LOAN_ACCUMULATE_SAME": 0.93925704
    },
    {
      "REPORT_DATE": "2008-07-01 00:00:00",
      "TIME": "2008年07月份",
      "RMB_LOAN": 3818,
      "RMB_LOAN_SAME": 64.99567848,
      "RMB_LOAN_SEQUENTIAL": 14.86161252,
      "RMB_LOAN_ACCUMULATE": 28343,
      "LOAN_ACCUMULATE_SAME": 2.17375631
    },
    {
      "REPORT_DATE": "2008-06-01 00:00:00",
      "TIME": "2008年06月份",
      "RMB_LOAN": 3324,
      "RMB_LOAN_SAME": -26.37873754,
      "RMB_LOAN_SEQUENTIAL": 4.36420722,
      "RMB_LOAN_ACCUMULATE": 24525,
      "LOAN_ACCUMULATE_SAME": -3.54361677
    },
    {
      "REPORT_DATE": "2008-05-01 00:00:00",
      "TIME": "2008年05月份",
      "RMB_LOAN": 3185,
      "RMB_LOAN_SAME": 28.79094218,
      "RMB_LOAN_SEQUENTIAL": -32.08955224,
      "RMB_LOAN_ACCUMULATE": 21201,
      "LOAN_ACCUMULATE_SAME": 1.3868299
    },
    {
      "REPORT_DATE": "2008-04-01 00:00:00",
      "TIME": "2008年04月份",
      "RMB_LOAN": 4690,
      "RMB_LOAN_SAME": 11.13744076,
      "RMB_LOAN_SEQUENTIAL": 65.49047283,
      "RMB_LOAN_ACCUMULATE": 18016,
      "LOAN_ACCUMULATE_SAME": -2.28875149
    },
    {
      "REPORT_DATE": "2008-03-01 00:00:00",
      "TIME": "2008年03月份",
      "RMB_LOAN": 2834,
      "RMB_LOAN_SAME": -35.83880462,
      "RMB_LOAN_SEQUENTIAL": 16.43385374,
      "RMB_LOAN_ACCUMULATE": 13326,
      "LOAN_ACCUMULATE_SAME": -6.27373752
    },
    {
      "REPORT_DATE": "2008-02-01 00:00:00",
      "TIME": "2008年02月份",
      "RMB_LOAN": 2434,
      "RMB_LOAN_SAME": -41.17931368,
      "RMB_LOAN_SEQUENTIAL": -69.79399355,
      "RMB_LOAN_ACCUMULATE": 10492,
      "LOAN_ACCUMULATE_SAME": 7.05030099
    },
    {
      "REPORT_DATE": "2008-01-01 00:00:00",
      "TIME": "2008年01月份",
      "RMB_LOAN": 8058,
      "RMB_LOAN_SAME": 42.29207134,
      "RMB_LOAN_SEQUENTIAL": 1561.44329897,
      "RMB_LOAN_ACCUMULATE": 8058,
      "LOAN_ACCUMULATE_SAME": 42.29207134
    }
  ]
}
